jupyterlite_webr/__init__.py
jupyterlite_webr/_version.py
jupyterlite_webr-0.6.0.data/data/share/jupyter/labextensions/@r-wasm/jupyterlite-webr-kernel/build_log.json
jupyterlite_webr-0.6.0.data/data/share/jupyter/labextensions/@r-wasm/jupyterlite-webr-kernel/package.json
jupyterlite_webr-0.6.0.data/data/share/jupyter/labextensions/@r-wasm/jupyterlite-webr-kernel/static/c0aaa09171ee16729b12a148c532baa8.png
jupyterlite_webr-0.6.0.data/data/share/jupyter/labextensions/@r-wasm/jupyterlite-webr-kernel/static/da1166e72a7daee41c4b332dd06e206d.png
jupyterlite_webr-0.6.0.data/data/share/jupyter/labextensions/@r-wasm/jupyterlite-webr-kernel/static/lib_index_js.f962e1f2278186c03601.js
jupyterlite_webr-0.6.0.data/data/share/jupyter/labextensions/@r-wasm/jupyterlite-webr-kernel/static/lib_index_js.f962e1f2278186c03601.js.map
jupyterlite_webr-0.6.0.data/data/share/jupyter/labextensions/@r-wasm/jupyterlite-webr-kernel/static/node_modules_webr_dist_sync_recursive.9f4eb224fc3af63c5e07.js
jupyterlite_webr-0.6.0.data/data/share/jupyter/labextensions/@r-wasm/jupyterlite-webr-kernel/static/node_modules_webr_dist_sync_recursive.9f4eb224fc3af63c5e07.js.map
jupyterlite_webr-0.6.0.data/data/share/jupyter/labextensions/@r-wasm/jupyterlite-webr-kernel/static/remoteEntry.7690036a599837aed2a8.js
jupyterlite_webr-0.6.0.data/data/share/jupyter/labextensions/@r-wasm/jupyterlite-webr-kernel/static/remoteEntry.7690036a599837aed2a8.js.map
jupyterlite_webr-0.6.0.data/data/share/jupyter/labextensions/@r-wasm/jupyterlite-webr-kernel/static/style.js
jupyterlite_webr-0.6.0.data/data/share/jupyter/labextensions/@r-wasm/jupyterlite-webr-kernel/static/style_index_js.261c102787d911ff26ed.js
jupyterlite_webr-0.6.0.data/data/share/jupyter/labextensions/@r-wasm/jupyterlite-webr-kernel/static/vendors-node_modules_jupyterlite_server_lib_index_js.0e6adbc28c789d135661.js
jupyterlite_webr-0.6.0.dist-info/METADATA
jupyterlite_webr-0.6.0.dist-info/WHEEL
jupyterlite_webr-0.6.0.dist-info/licenses/LICENSE
jupyterlite_webr-0.6.0.dist-info/RECORD
