Metadata-Version: 2.4
Name: jupyterlite-webr
Version: 0.6.0
Dynamic: Keywords
Summary: An R kernel for JupyterLite, powered by webR
Project-URL: Homepage, https://github.com/r-wasm/jupyterlite-webr-kernel
Project-URL: Bug Tracker, https://github.com/r-wasm/jupyterlite-webr-kernel/issues
Project-URL: Repository, https://github.com/r-wasm/jupyterlite-webr-kernel.git
Author-email: George Stagg <george.stagg@posit.co>
License: Copyright 2023 jupyterlite-webr-kernel authors
License-File: LICENSE
Classifier: Framework :: Jupyter
Classifier: Framework :: Jupyter :: JupyterLab
Classifier: Framework :: Jupyter :: JupyterLab :: 4
Classifier: Framework :: Jupyter :: JupyterLab :: Extensions
Classifier: Framework :: Jupyter :: JupyterLab :: Extensions :: Prebuilt
Classifier: License :: OSI Approved :: MIT License
Classifier: Programming Language :: Python
Classifier: Programming Language :: Python :: 3
Classifier: Programming Language :: Python :: 3.9
Classifier: Programming Language :: Python :: 3.10
Classifier: Programming Language :: Python :: 3.11
Classifier: Programming Language :: Python :: 3.12
Classifier: Programming Language :: Python :: 3.13
Requires-Python: >=3.9
Requires-Dist: jupyterlite-core<0.7,>=0.6
Provides-Extra: dev
Requires-Dist: jupyterlab<4.5,>=4.4.0; extra == 'dev'
Requires-Dist: jupyterlite-pyodide-kernel>=0.6.1; extra == 'dev'
Requires-Dist: pkginfo>=1.10.0; extra == 'dev'
Requires-Dist: ruff==0.1.5; extra == 'dev'
